amro/__init__.py
amro/config/__init__.py
amro/config/cleaner.py
amro/config/headers.py
amro/config/paths.py
amro/config/plotting.py
amro/config/settings.py
amro/data/__init__.py
amro/data/cleaner.py
amro/data/data_structures.py
amro/data/loader.py
amro/features/__init__.py
amro/features/fourier.py
amro/models/__init__.py
amro/models/fitter.py
amro/plotting/__init__.py
amro/plotting/fitter.py
amro/plotting/fourier.py
amro/plotting/loader.py
amro/utils/__init__.py
amro/utils/conversions.py
amro/utils/utils.py
amro-0.1.0.dist-info/licenses/LICENSE
amro-0.1.0.dist-info/METADATA
amro-0.1.0.dist-info/WHEEL
amro-0.1.0.dist-info/top_level.txt
amro-0.1.0.dist-info/RECORD
