Metadata-Version: 2.4
Name: amro
Version: 0.1.0
Summary: Angle-resolved Magnetoresistance Oscillation (AMRO) Analysis by Fourier transform and best fit.
Author: James Fraser
Author-email: James Fraser <james.fraser@umontreal.ca>
Maintainer-email: James Fraser <james.fraser@umontreal.ca>
License: MIT
Project-URL: Homepage, https://github.com/BaconBaconBacon/AMRO-Analysis
Project-URL: Repository, https://github.com/BaconBaconBacon/AMRO-Analysis
Project-URL: Issues, https://github.com/BaconBaconBacon/AMRO-Analysis/issues
Keywords: physics,condensed-matter,fermi-surface,magnetoresistance,amr,amro
Classifier: Development Status :: 3 - Alpha
Classifier: Intended Audience :: Science/Research
Classifier: License :: OSI Approved :: MIT License
Classifier: Programming Language :: Python :: 3
Classifier: Programming Language :: Python :: 3.9
Classifier: Programming Language :: Python :: 3.10
Classifier: Programming Language :: Python :: 3.11
Classifier: Topic :: Scientific/Engineering :: Physics
Requires-Python: >=3.9
License-File: LICENSE
Requires-Dist: numpy
Requires-Dist: pandas
Requires-Dist: scipy
Requires-Dist: matplotlib
Requires-Dist: seaborn
Requires-Dist: lmfit
Provides-Extra: dev
Requires-Dist: pytest; extra == "dev"
Requires-Dist: jupyter; extra == "dev"
Requires-Dist: ipython; extra == "dev"
Dynamic: author
Dynamic: license-file
Dynamic: requires-python
